[
  {
    "time": [
      {
        "value": 2015,
        "unit": "年"
      },
      {
        "value": 8,
        "unit": "月"
      },
      {
        "value": 30,
        "unit": "日"
      },
      {
        "value": 8,
        "unit": "时"
      },
      {
        "value": 8,
        "unit": "分"
      }
    ],
    "symptom": [
      "sdaf"
    ]
  },
  {
    "time": [
      {
        "value": 1994,
        "unit": "年"
      },
      {
        "value": 8,
        "unit": "月"
      },
      {
        "value": 30,
        "unit": "日"
      },
      {
        "value": 20,
        "unit": "时"
      },
      {
        "value": 8,
        "unit": "分"
      }
    ],
    "symptom": [
      "saf"
    ]
  },
  {
    "time": [
      {
        "value": 3,
        "unit": "岁"
      }
    ],
    "symptom": [
      "sdaf"
    ]
  }
]